LICENSE
MANIFEST.in
README.rst
setup.py
LowVoltage/__init__.py
LowVoltage/attribute_types.py
LowVoltage/exceptions.py
LowVoltage/variadic.py
LowVoltage.egg-info/PKG-INFO
LowVoltage.egg-info/SOURCES.txt
LowVoltage.egg-info/dependency_links.txt
LowVoltage.egg-info/requires.txt
LowVoltage.egg-info/top_level.txt
LowVoltage/actions/__init__.py
LowVoltage/actions/action.py
LowVoltage/actions/batch_get_item.py
LowVoltage/actions/batch_write_item.py
LowVoltage/actions/conversion.py
LowVoltage/actions/create_table.py
LowVoltage/actions/delete_item.py
LowVoltage/actions/delete_table.py
LowVoltage/actions/describe_table.py
LowVoltage/actions/expressions.py
LowVoltage/actions/get_item.py
LowVoltage/actions/list_tables.py
LowVoltage/actions/next_gen_mixins.py
LowVoltage/actions/put_item.py
LowVoltage/actions/query.py
LowVoltage/actions/return_types.py
LowVoltage/actions/scan.py
LowVoltage/actions/update_item.py
LowVoltage/actions/update_table.py
LowVoltage/actions/tests/__init__.py
LowVoltage/actions/tests/unit.py
LowVoltage/actions/tests/integ/__init__.py
LowVoltage/actions/tests/integ/connected.py
LowVoltage/actions/tests/integ/local.py
LowVoltage/actions/tests/integ/test_batch_get_item.py
LowVoltage/actions/tests/integ/test_batch_write_item.py
LowVoltage/actions/tests/integ/test_create_table.py
LowVoltage/actions/tests/integ/test_delete_item.py
LowVoltage/actions/tests/integ/test_delete_table.py
LowVoltage/actions/tests/integ/test_describe_table.py
LowVoltage/actions/tests/integ/test_get_item.py
LowVoltage/actions/tests/integ/test_list_tables.py
LowVoltage/actions/tests/integ/test_put_item.py
LowVoltage/actions/tests/integ/test_query.py
LowVoltage/actions/tests/integ/test_scan.py
LowVoltage/actions/tests/integ/test_update_item.py
LowVoltage/actions/tests/integ/test_update_table.py
LowVoltage/compounds/__init__.py
LowVoltage/compounds/batch_delete_item.py
LowVoltage/compounds/batch_put_item.py
LowVoltage/compounds/iterate_batch_get_item.py
LowVoltage/compounds/iterate_list_tables.py
LowVoltage/compounds/iterate_query.py
LowVoltage/compounds/iterate_scan.py
LowVoltage/compounds/wait_for_table_activation.py
