Metadata-Version: 1.1
Name: LowVoltage
Version: 0.7.3
Summary: Standalone DynamoDB client not hiding any feature
Home-page: http://pythonhosted.org/LowVoltage
Author: Vincent Jacques
Author-email: vincent@vincent-jacques.net
License: MIT
Platform: UNKNOWN
Classifier: Development Status :: 4 - Beta
Classifier: Environment :: Web Environment
Classifier: Intended Audience :: Developers
Classifier: License :: OSI Approved
Classifier: License :: OSI Approved :: MIT License
Classifier: Operating System :: OS Independent
Classifier: Programming Language :: Python
Classifier: Programming Language :: Python :: 2
Classifier: Programming Language :: Python :: 2.7
Classifier: Programming Language :: Python :: 3
Classifier: Programming Language :: Python :: 3.4
Classifier: Topic :: Database
